psql2mysql/__init__.py
psql2mysql/datetime2decimal.py
psql2mysql/tests/__init__.py
psql2mysql/tests/test_dbdatamigrator.py
psql2mysql/tests/test_dbwrapper.py
psql2mysql-0.5.1.dist-info/AUTHORS
psql2mysql-0.5.1.dist-info/LICENSE
psql2mysql-0.5.1.dist-info/METADATA
psql2mysql-0.5.1.dist-info/WHEEL
psql2mysql-0.5.1.dist-info/entry_points.txt
psql2mysql-0.5.1.dist-info/pbr.json
psql2mysql-0.5.1.dist-info/top_level.txt
psql2mysql-0.5.1.dist-info/RECORD
