Metadata-Version: 2.1
Name: psql2mysql
Version: 0.5.1
Summary: Copy data from PostgreSQL databases to MySQL
Home-page: https://github.com/SUSE/psql2mysql
Author: UNKNOWN
Author-email: UNKNOWN
License: Apache-2
Platform: UNKNOWN
Classifier: Development Status :: 3 - Alpha
Classifier: Intended Audience :: Developers
Classifier: License :: OSI Approved :: Apache Software License
Classifier: Programming Language :: Python :: 2
Classifier: Programming Language :: Python :: 2.7
Classifier: Programming Language :: Python :: 3
Classifier: Programming Language :: Python :: 3.5
Classifier: Programming Language :: Python :: 3.6
Requires-Dist: oslo.config
Requires-Dist: oslo.log
Requires-Dist: psycopg2
Requires-Dist: prettytable
Requires-Dist: PyMySQL
Requires-Dist: PyYAML
Requires-Dist: rfc3986
Requires-Dist: SQLAlchemy (<1.1.0,>=1.0.10)
